remind/__init__.py
remind/__main__.py
remind/error_handler.py
remind/query_manager.py
remind/reminder.py
remind/reminder_confirmation.py
remind/reminder_manager.py
remindmail-2024.7.23.1.dist-info/LICENSE.md
remindmail-2024.7.23.1.dist-info/METADATA
remindmail-2024.7.23.1.dist-info/WHEEL
remindmail-2024.7.23.1.dist-info/entry_points.txt
remindmail-2024.7.23.1.dist-info/top_level.txt
remindmail-2024.7.23.1.dist-info/RECORD
