Metadata-Version: 2.1
Name: remindmail
Version: 2024.7.23.1
Summary: Easily schedule reminders to be emailed
Home-page: https://github.com/tylerjwoodfin/remindmail
Author: Tyler Woodfin
Author-email: feedback-remindmail@tyler.cloud
License: : OSI Approved :: MIT License
Requires-Python: >=3.6
License-File: LICENSE.md
